nexaai/__init__.py
nexaai/_stub.cpython-310-darwin.so
nexaai/_version.py
nexaai/asr.py
nexaai/base.py
nexaai/common.py
nexaai/cv.py
nexaai/diarize.py
nexaai/embedder.py
nexaai/image_gen.py
nexaai/llm.py
nexaai/log.py
nexaai/rerank.py
nexaai/runtime.py
nexaai/runtime_error.py
nexaai/tts.py
nexaai/vlm.py
nexaai/asr_impl/__init__.py
nexaai/asr_impl/mlx_asr_impl.py
nexaai/asr_impl/pybind_asr_impl.py
nexaai/binds/__init__.py
nexaai/binds/asr_bind.cpython-310-darwin.so
nexaai/binds/common_bind.cpython-310-darwin.so
nexaai/binds/cv_bind.cpython-310-darwin.so
nexaai/binds/diarize_bind.cpython-310-darwin.so
nexaai/binds/embedder_bind.cpython-310-darwin.so
nexaai/binds/libnexa_bridge.dylib
nexaai/binds/llm_bind.cpython-310-darwin.so
nexaai/binds/rerank_bind.cpython-310-darwin.so
nexaai/binds/vlm_bind.cpython-310-darwin.so
nexaai/binds/cpu_gpu/libggml-base.dylib
nexaai/binds/cpu_gpu/libggml-cpu.so
nexaai/binds/cpu_gpu/libggml-metal.so
nexaai/binds/cpu_gpu/libggml.dylib
nexaai/binds/cpu_gpu/libmtmd.dylib
nexaai/binds/cpu_gpu/libnexa_cpu_gpu.dylib
nexaai/binds/cpu_gpu/libnexa_plugin.dylib
nexaai/binds/metal/libnexa_plugin.dylib
nexaai/binds/metal/py-lib/ml.py
nexaai/binds/metal/py-lib/profiling.py
nexaai/binds/metal/py-lib/mlx_audio/__init__.py
nexaai/binds/metal/py-lib/mlx_audio/server.py
nexaai/binds/metal/py-lib/mlx_audio/utils.py
nexaai/binds/metal/py-lib/mlx_audio/version.py
nexaai/binds/metal/py-lib/mlx_audio/codec/__init__.py
nexaai/binds/metal/py-lib/mlx_audio/codec/models/__init__.py
nexaai/binds/metal/py-lib/mlx_audio/codec/models/bigvgan/__init__.py
nexaai/binds/metal/py-lib/mlx_audio/codec/models/bigvgan/activation.py
nexaai/binds/metal/py-lib/mlx_audio/codec/models/bigvgan/amp.py
nexaai/binds/metal/py-lib/mlx_audio/codec/models/bigvgan/bigvgan.py
nexaai/binds/metal/py-lib/mlx_audio/codec/models/bigvgan/conv.py
nexaai/binds/metal/py-lib/mlx_audio/codec/models/bigvgan/resample.py
nexaai/binds/metal/py-lib/mlx_audio/codec/models/descript/__init__.py
nexaai-1.0.29.dist-info/METADATA
nexaai-1.0.29.dist-info/WHEEL
nexaai-1.0.29.dist-info/top_level.txt
nexaai-1.0.29.dist-info/RECORD
