Metadata-Version: 2.4
Name: nexaai
Version: 1.0.29
Summary: Python bindings for NexaSDK C-lib backend
Author-email: "Nexa AI, Inc." <dev@nexa.ai>
Project-URL: Homepage, https://github.com/NexaAI/nexasdk-bridge
Classifier: Programming Language :: Python :: 3
Classifier: License :: OSI Approved :: MIT License
Classifier: Operating System :: OS Independent
Classifier: Development Status :: 4 - Beta
Classifier: Intended Audience :: Developers
Classifier: Topic :: Software Development :: Libraries :: Python Modules
Requires-Python: >=3.7
Requires-Dist: huggingface_hub
Requires-Dist: tqdm
Requires-Dist: numpy
Requires-Dist: httpx
Provides-Extra: mlx
Requires-Dist: mlx; extra == "mlx"
Requires-Dist: mlx-lm==0.27.0; extra == "mlx"
Requires-Dist: mlx-vlm; extra == "mlx"
Requires-Dist: mlx-embeddings; extra == "mlx"
Requires-Dist: tokenizers; extra == "mlx"
Requires-Dist: safetensors; extra == "mlx"
Requires-Dist: Pillow; extra == "mlx"
Requires-Dist: scipy; extra == "mlx"
Requires-Dist: soundfile; extra == "mlx"
Requires-Dist: opencv-python; extra == "mlx"
Requires-Dist: shapely; extra == "mlx"
Requires-Dist: pyclipper; extra == "mlx"
Requires-Dist: transformers; extra == "mlx"
Requires-Dist: tiktoken; extra == "mlx"
Requires-Dist: numba; extra == "mlx"
Requires-Dist: dacite; extra == "mlx"
